dracclient/__init__.py
dracclient/client.py
dracclient/constants.py
dracclient/exceptions.py
dracclient/utils.py
dracclient/wsman.py
dracclient/resources/__init__.py
dracclient/resources/bios.py
dracclient/resources/idrac_card.py
dracclient/resources/inventory.py
dracclient/resources/job.py
dracclient/resources/lifecycle_controller.py
dracclient/resources/nic.py
dracclient/resources/raid.py
dracclient/resources/system.py
dracclient/resources/uris.py
dracclient/tests/__init__.py
dracclient/tests/base.py
dracclient/tests/test_bios.py
dracclient/tests/test_client.py
dracclient/tests/test_idrac_card.py
dracclient/tests/test_inventory.py
dracclient/tests/test_job.py
dracclient/tests/test_lifecycle_controller.py
dracclient/tests/test_nic.py
dracclient/tests/test_raid.py
dracclient/tests/test_system.py
dracclient/tests/test_utils.py
dracclient/tests/test_wsman.py
dracclient/tests/utils.py
dracclient/tests/wsman_mocks/bios_enumeration-enum-ok.xml
dracclient/tests/wsman_mocks/bios_integer-enum-mutable.xml
dracclient/tests/wsman_mocks/bios_integer-enum-ok.xml
dracclient/tests/wsman_mocks/bios_service-invoke-create_targeted_config_job-error.xml
dracclient/tests/wsman_mocks/bios_service-invoke-create_targeted_config_job-ok.xml
dracclient/tests/wsman_mocks/bios_service-invoke-delete_pending_configuration-error.xml
dracclient/tests/wsman_mocks/bios_service-invoke-delete_pending_configuration-ok.xml
dracclient/tests/wsman_mocks/bios_service-invoke-set_attributes-error.xml
dracclient/tests/wsman_mocks/bios_service-invoke-set_attributes-ok.xml
dracclient/tests/wsman_mocks/bios_string-enum-colliding.xml
dracclient/tests/wsman_mocks/bios_string-enum-ok.xml
dracclient/tests/wsman_mocks/bios_string-enum-regexp.xml
dracclient/tests/wsman_mocks/boot_config_setting-enum-ok.xml
dracclient/tests/wsman_mocks/boot_config_setting-invoke-change_boot_order_by_instance_id-error.xml
dracclient/tests/wsman_mocks/boot_config_setting-invoke-change_boot_order_by_instance_id-ok.xml
python_dracclient-8.0.0.dist-info/AUTHORS
python_dracclient-8.0.0.dist-info/LICENSE
python_dracclient-8.0.0.dist-info/METADATA
python_dracclient-8.0.0.dist-info/WHEEL
python_dracclient-8.0.0.dist-info/pbr.json
python_dracclient-8.0.0.dist-info/top_level.txt
python_dracclient-8.0.0.dist-info/RECORD
