Metadata-Version: 2.1
Name: python-dracclient
Version: 8.0.0
Summary: Library for managing machines with Dell iDRAC cards
Home-page: https://launchpad.net/python-dracclient
Author-email: openstack-discuss@lists.openstack.org
Maintainer: DracClient Team
License: Apache-2
Platform: UNKNOWN
Classifier: Intended Audience :: Developers
Classifier: Intended Audience :: Information Technology
Classifier: License :: OSI Approved :: Apache Software License
Classifier: Operating System :: POSIX
Classifier: Programming Language :: Python
Classifier: Programming Language :: Python :: 3
Classifier: Programming Language :: Python :: 3.6
Classifier: Programming Language :: Python :: 3.7
Classifier: Programming Language :: Python :: 3.8
Classifier: Programming Language :: Python :: 3.9
Requires-Dist: lxml (>=2.3)
Requires-Dist: pbr (>=1.6)
Requires-Dist: requests (>=2.10.0)
